ecp_cookie_init/__init__.py
ecp_cookie_init/__main__.py
ecp_cookie_init/tests/__init__.py
ecp_cookie_init/tests/test_ecp_cookie_init.py
ecp_cookie_init-2.0.1.dist-info/COPYING
ecp_cookie_init-2.0.1.dist-info/METADATA
ecp_cookie_init-2.0.1.dist-info/WHEEL
ecp_cookie_init-2.0.1.dist-info/entry_points.txt
ecp_cookie_init-2.0.1.dist-info/top_level.txt
ecp_cookie_init-2.0.1.dist-info/RECORD
